<?xml version="1.0" encoding="UTF-8" standalone="yes"?><p:sld xmlns:a="http://schemas.openxmlformats.org/drawingml/2006/main" xmlns:r="http://schemas.openxmlformats.org/officeDocument/2006/relationships" xmlns:p="http://schemas.openxmlformats.org/presentationml/2006/main"><p:cSld><p:bg><p:bgPr><a:solidFill><a:srgbClr val="1A1A2E"/></a:solidFill><a:effectLst/></p:bgPr></p:bg><p:spTree><p:nvGrpSpPr><p:cNvPr id="1" name=""/><p:cNvGrpSpPr/><p:nvPr/></p:nvGrpSpPr><p:grpSpPr><a:xfrm><a:off x="0" y="0"/><a:ext cx="0" cy="0"/><a:chOff x="0" y="0"/><a:chExt cx="0" cy="0"/></a:xfrm></p:grpSpPr><p:sp><p:nvSpPr><p:cNvPr id="2" name="rect2"/><p:cNvSpPr/><p:nvPr/></p:nvSpPr><p:spPr><a:xfrm><a:off x="0" y="0"/><a:ext cx="12188952" cy="1005840"/></a:xfrm><a:prstGeom prst="rect"><a:avLst/></a:prstGeom><a:solidFill><a:srgbClr val="E94F37"/></a:solidFill><a:ln><a:noFill/></a:ln></p:spPr><p:txBody><a:bodyPr/><a:lstStyle/><a:p><a:endParaRPr/></a:p></p:txBody></p:sp><p:sp><p:nvSpPr><p:cNvPr id="3" name="Title"/><p:cNvSpPr txBox="1"/><p:nvPr/></p:nvSpPr><p:spPr><a:xfrm><a:off x="274320" y="91440"/><a:ext cx="9500000" cy="640080"/></a:xfrm><a:prstGeom prst="rect"><a:avLst/></a:prstGeom><a:noFill/><a:ln><a:noFill/></a:ln></p:spPr><p:txBody><a:bodyPr wrap="square" lIns="91440" rIns="91440" tIns="45720" bIns="45720"><a:spAutoFit/></a:bodyPr><a:lstStyle/><a:p><a:pPr algn="l" indent="0" marL="0" spc="-100"/><a:r><a:rPr sz="3200" b="1" dirty="0"><a:solidFill><a:srgbClr val="FFFFFF"/></a:solidFill></a:rPr><a:t>PlayerController — 코드 구조</a:t></a:r></a:p></p:txBody></p:sp><p:sp><p:nvSpPr><p:cNvPr id="4" name="Sub"/><p:cNvSpPr txBox="1"/><p:nvPr/></p:nvSpPr><p:spPr><a:xfrm><a:off x="274320" y="685800"/><a:ext cx="10972800" cy="365760"/></a:xfrm><a:prstGeom prst="rect"><a:avLst/></a:prstGeom><a:noFill/><a:ln><a:noFill/></a:ln></p:spPr><p:txBody><a:bodyPr wrap="square" lIns="91440" rIns="91440" tIns="45720" bIns="45720"><a:spAutoFit/></a:bodyPr><a:lstStyle/><a:p><a:pPr algn="l" indent="0" marL="0" spc="-100"/><a:r><a:rPr sz="1300" b="0" dirty="0"><a:solidFill><a:srgbClr val="FFEECC"/></a:solidFill></a:rPr><a:t>Code Architecture</a:t></a:r></a:p></p:txBody></p:sp><p:sp><p:nvSpPr><p:cNvPr id="5" name="LT1"/><p:cNvSpPr txBox="1"/><p:nvPr/></p:nvSpPr><p:spPr><a:xfrm><a:off x="274320" y="1130000"/><a:ext cx="5500000" cy="380000"/></a:xfrm><a:prstGeom prst="rect"><a:avLst/></a:prstGeom><a:noFill/><a:ln><a:noFill/></a:ln></p:spPr><p:txBody><a:bodyPr wrap="square" lIns="91440" rIns="91440" tIns="45720" bIns="45720"><a:spAutoFit/></a:bodyPr><a:lstStyle/><a:p><a:pPr algn="l" indent="0" marL="0" spc="-100"/><a:r><a:rPr sz="1500" b="1" dirty="0"><a:solidFill><a:srgbClr val="E94F37"/></a:solidFill></a:rPr><a:t>partial class 4분할 구조</a:t></a:r></a:p></p:txBody></p:sp><p:sp><p:nvSpPr><p:cNvPr id="6" name="rect6"/><p:cNvSpPr/><p:nvPr/></p:nvSpPr><p:spPr><a:xfrm><a:off x="274320" y="1510000"/><a:ext cx="5500000" cy="2200000"/></a:xfrm><a:prstGeom prst="rect"><a:avLst/></a:prstGeom><a:solidFill><a:srgbClr val="0A0A1A"/></a:solidFill><a:ln><a:noFill/></a:ln></p:spPr><p:txBody><a:bodyPr/><a:lstStyle/><a:p><a:endParaRPr/></a:p></p:txBody></p:sp><p:sp><p:nvSpPr><p:cNvPr id="7" name="LC1"/><p:cNvSpPr txBox="1"/><p:nvPr/></p:nvSpPr><p:spPr><a:xfrm><a:off x="365760" y="1556720"/><a:ext cx="5318400" cy="2153280"/></a:xfrm><a:prstGeom prst="rect"><a:avLst/></a:prstGeom><a:noFill/><a:ln><a:noFill/></a:ln></p:spPr><p:txBody><a:bodyPr wrap="square" lIns="91440" rIns="91440" tIns="45720" bIns="45720"><a:spAutoFit/></a:bodyPr><a:lstStyle/><a:p><a:pPr algn="l" indent="0" marL="0" spc="-100"/><a:r><a:rPr sz="850" b="0" dirty="0"><a:solidFill><a:srgbClr val="888888"/></a:solidFill><a:latin typeface="Consolas"/></a:rPr><a:t>// PlayerController.cs</a:t></a:r></a:p><a:p><a:pPr algn="l" indent="0" marL="0" spc="-100"/><a:r><a:rPr sz="850" b="0" dirty="0"><a:solidFill><a:srgbClr val="66D9EF"/></a:solidFill><a:latin typeface="Consolas"/></a:rPr><a:t>[RequireComponent(typeof(Rigidbody2D))]</a:t></a:r></a:p><a:p><a:pPr algn="l" indent="0" marL="0" spc="-100"/><a:r><a:rPr sz="850" b="0" dirty="0"><a:solidFill><a:srgbClr val="FD971F"/></a:solidFill><a:latin typeface="Consolas"/></a:rPr><a:t>public partial class PlayerController : MonoBehaviour</a:t></a:r></a:p><a:p><a:pPr algn="l" indent="0" marL="0" spc="-100"/><a:r><a:rPr sz="850" b="0" dirty="0"><a:solidFill><a:srgbClr val="FFFFFF"/></a:solidFill><a:latin typeface="Consolas"/></a:rPr><a:t>{</a:t></a:r></a:p><a:p><a:pPr algn="l" indent="0" marL="0" spc="-100"/><a:r><a:rPr sz="850" b="0" dirty="0"><a:solidFill><a:srgbClr val="888888"/></a:solidFill><a:latin typeface="Consolas"/></a:rPr><a:t>    // 필드, Awake, Start, Update, FixedUpdate</a:t></a:r></a:p><a:p><a:pPr algn="l" indent="0" marL="0" spc="-100"/><a:r><a:rPr sz="850" b="0" dirty="0"><a:solidFill><a:srgbClr val="888888"/></a:solidFill><a:latin typeface="Consolas"/></a:rPr><a:t>    // 물리 감지: UpdatePhysicsState()</a:t></a:r></a:p><a:p><a:pPr algn="l" indent="0" marL="0" spc="-100"/><a:r><a:rPr sz="850" b="0" dirty="0"><a:solidFill><a:srgbClr val="FFFFFF"/></a:solidFill><a:latin typeface="Consolas"/></a:rPr><a:t>}</a:t></a:r></a:p><a:p><a:pPr spc="-100"/><a:endParaRPr/></a:p><a:p><a:pPr algn="l" indent="0" marL="0" spc="-100"/><a:r><a:rPr sz="850" b="0" dirty="0"><a:solidFill><a:srgbClr val="888888"/></a:solidFill><a:latin typeface="Consolas"/></a:rPr><a:t>// .Input.cs   — Input System 콜백</a:t></a:r></a:p><a:p><a:pPr algn="l" indent="0" marL="0" spc="-100"/><a:r><a:rPr sz="850" b="0" dirty="0"><a:solidFill><a:srgbClr val="888888"/></a:solidFill><a:latin typeface="Consolas"/></a:rPr><a:t>// .Movement.cs — Jump / Dash / WallJump</a:t></a:r></a:p><a:p><a:pPr algn="l" indent="0" marL="0" spc="-100"/><a:r><a:rPr sz="850" b="0" dirty="0"><a:solidFill><a:srgbClr val="888888"/></a:solidFill><a:latin typeface="Consolas"/></a:rPr><a:t>// .Combat.cs  — TakeDamage / Attack / Die</a:t></a:r></a:p></p:txBody></p:sp><p:sp><p:nvSpPr><p:cNvPr id="8" name="LT2"/><p:cNvSpPr txBox="1"/><p:nvPr/></p:nvSpPr><p:spPr><a:xfrm><a:off x="274320" y="3810000"/><a:ext cx="5500000" cy="380000"/></a:xfrm><a:prstGeom prst="rect"><a:avLst/></a:prstGeom><a:noFill/><a:ln><a:noFill/></a:ln></p:spPr><p:txBody><a:bodyPr wrap="square" lIns="91440" rIns="91440" tIns="45720" bIns="45720"><a:spAutoFit/></a:bodyPr><a:lstStyle/><a:p><a:pPr algn="l" indent="0" marL="0" spc="-100"/><a:r><a:rPr sz="1500" b="1" dirty="0"><a:solidFill><a:srgbClr val="E94F37"/></a:solidFill></a:rPr><a:t>물리 감지 — GetContacts 기반</a:t></a:r></a:p></p:txBody></p:sp><p:sp><p:nvSpPr><p:cNvPr id="9" name="rect9"/><p:cNvSpPr/><p:nvPr/></p:nvSpPr><p:spPr><a:xfrm><a:off x="274320" y="4190000"/><a:ext cx="5500000" cy="2350000"/></a:xfrm><a:prstGeom prst="rect"><a:avLst/></a:prstGeom><a:solidFill><a:srgbClr val="0A0A1A"/></a:solidFill><a:ln><a:noFill/></a:ln></p:spPr><p:txBody><a:bodyPr/><a:lstStyle/><a:p><a:endParaRPr/></a:p></p:txBody></p:sp><p:sp><p:nvSpPr><p:cNvPr id="10" name="LC2"/><p:cNvSpPr txBox="1"/><p:nvPr/></p:nvSpPr><p:spPr><a:xfrm><a:off x="365760" y="4236720"/><a:ext cx="5318400" cy="2303280"/></a:xfrm><a:prstGeom prst="rect"><a:avLst/></a:prstGeom><a:noFill/><a:ln><a:noFill/></a:ln></p:spPr><p:txBody><a:bodyPr wrap="square" lIns="91440" rIns="91440" tIns="45720" bIns="45720"><a:spAutoFit/></a:bodyPr><a:lstStyle/><a:p><a:pPr algn="l" indent="0" marL="0" spc="-100"/><a:r><a:rPr sz="850" b="0" dirty="0"><a:solidFill><a:srgbClr val="FD971F"/></a:solidFill><a:latin typeface="Consolas"/></a:rPr><a:t>void UpdatePhysicsState() {</a:t></a:r></a:p><a:p><a:pPr algn="l" indent="0" marL="0" spc="-100"/><a:r><a:rPr sz="850" b="0" dirty="0"><a:solidFill><a:srgbClr val="A8FF78"/></a:solidFill><a:latin typeface="Consolas"/></a:rPr><a:t>    int cnt = _rb.GetContacts(_contacts);</a:t></a:r></a:p><a:p><a:pPr algn="l" indent="0" marL="0" spc="-100"/><a:r><a:rPr sz="850" b="0" dirty="0"><a:solidFill><a:srgbClr val="A8FF78"/></a:solidFill><a:latin typeface="Consolas"/></a:rPr><a:t>    for (int i = 0; i < cnt; i++) {</a:t></a:r></a:p><a:p><a:pPr algn="l" indent="0" marL="0" spc="-100"/><a:r><a:rPr sz="850" b="0" dirty="0"><a:solidFill><a:srgbClr val="888888"/></a:solidFill><a:latin typeface="Consolas"/></a:rPr><a:t>        // 법선 Y > 0.8 → 지면</a:t></a:r></a:p><a:p><a:pPr algn="l" indent="0" marL="0" spc="-100"/><a:r><a:rPr sz="850" b="0" dirty="0"><a:solidFill><a:srgbClr val="A8FF78"/></a:solidFill><a:latin typeface="Consolas"/></a:rPr><a:t>        if (_contacts[i].normal.y > 0.8f)</a:t></a:r></a:p><a:p><a:pPr algn="l" indent="0" marL="0" spc="-100"/><a:r><a:rPr sz="850" b="0" dirty="0"><a:solidFill><a:srgbClr val="A8FF78"/></a:solidFill><a:latin typeface="Consolas"/></a:rPr><a:t>            _isGrounded = true;</a:t></a:r></a:p><a:p><a:pPr algn="l" indent="0" marL="0" spc="-100"/><a:r><a:rPr sz="850" b="0" dirty="0"><a:solidFill><a:srgbClr val="888888"/></a:solidFill><a:latin typeface="Consolas"/></a:rPr><a:t>        // 법선 X > 0.8 → 벽 (Enemy 제외)</a:t></a:r></a:p><a:p><a:pPr algn="l" indent="0" marL="0" spc="-100"/><a:r><a:rPr sz="850" b="0" dirty="0"><a:solidFill><a:srgbClr val="A8FF78"/></a:solidFill><a:latin typeface="Consolas"/></a:rPr><a:t>        if (Mathf.Abs(_contacts[i].normal.x) > 0.8f)</a:t></a:r></a:p><a:p><a:pPr algn="l" indent="0" marL="0" spc="-100"/><a:r><a:rPr sz="850" b="0" dirty="0"><a:solidFill><a:srgbClr val="A8FF78"/></a:solidFill><a:latin typeface="Consolas"/></a:rPr><a:t>            _isOnWall = true;</a:t></a:r></a:p><a:p><a:pPr algn="l" indent="0" marL="0" spc="-100"/><a:r><a:rPr sz="850" b="0" dirty="0"><a:solidFill><a:srgbClr val="A8FF78"/></a:solidFill><a:latin typeface="Consolas"/></a:rPr><a:t>    }</a:t></a:r></a:p><a:p><a:pPr algn="l" indent="0" marL="0" spc="-100"/><a:r><a:rPr sz="850" b="0" dirty="0"><a:solidFill><a:srgbClr val="FD971F"/></a:solidFill><a:latin typeface="Consolas"/></a:rPr><a:t>}</a:t></a:r></a:p></p:txBody></p:sp><p:sp><p:nvSpPr><p:cNvPr id="11" name="RT1"/><p:cNvSpPr txBox="1"/><p:nvPr/></p:nvSpPr><p:spPr><a:xfrm><a:off x="6100000" y="1130000"/><a:ext cx="5900000" cy="380000"/></a:xfrm><a:prstGeom prst="rect"><a:avLst/></a:prstGeom><a:noFill/><a:ln><a:noFill/></a:ln></p:spPr><p:txBody><a:bodyPr wrap="square" lIns="91440" rIns="91440" tIns="45720" bIns="45720"><a:spAutoFit/></a:bodyPr><a:lstStyle/><a:p><a:pPr algn="l" indent="0" marL="0" spc="-100"/><a:r><a:rPr sz="1500" b="1" dirty="0"><a:solidFill><a:srgbClr val="E94F37"/></a:solidFill></a:rPr><a:t>물리 기반 점프 — 정점 높이·시간 역산</a:t></a:r></a:p></p:txBody></p:sp><p:sp><p:nvSpPr><p:cNvPr id="12" name="rect12"/><p:cNvSpPr/><p:nvPr/></p:nvSpPr><p:spPr><a:xfrm><a:off x="6100000" y="1510000"/><a:ext cx="5900000" cy="2200000"/></a:xfrm><a:prstGeom prst="rect"><a:avLst/></a:prstGeom><a:solidFill><a:srgbClr val="0A0A1A"/></a:solidFill><a:ln><a:noFill/></a:ln></p:spPr><p:txBody><a:bodyPr/><a:lstStyle/><a:p><a:endParaRPr/></a:p></p:txBody></p:sp><p:sp><p:nvSpPr><p:cNvPr id="13" name="RC1"/><p:cNvSpPr txBox="1"/><p:nvPr/></p:nvSpPr><p:spPr><a:xfrm><a:off x="6191440" y="1556720"/><a:ext cx="5717280" cy="2153280"/></a:xfrm><a:prstGeom prst="rect"><a:avLst/></a:prstGeom><a:noFill/><a:ln><a:noFill/></a:ln></p:spPr><p:txBody><a:bodyPr wrap="square" lIns="91440" rIns="91440" tIns="45720" bIns="45720"><a:spAutoFit/></a:bodyPr><a:lstStyle/><a:p><a:pPr algn="l" indent="0" marL="0" spc="-100"/><a:r><a:rPr sz="850" b="0" dirty="0"><a:solidFill><a:srgbClr val="FD971F"/></a:solidFill><a:latin typeface="Consolas"/></a:rPr><a:t>void Jump() {</a:t></a:r></a:p><a:p><a:pPr algn="l" indent="0" marL="0" spc="-100"/><a:r><a:rPr sz="850" b="0" dirty="0"><a:solidFill><a:srgbClr val="A8FF78"/></a:solidFill><a:latin typeface="Consolas"/></a:rPr><a:t>    float v0 = 2f * maxJumpHeight / maxJumpApexTime;</a:t></a:r></a:p><a:p><a:pPr algn="l" indent="0" marL="0" spc="-100"/><a:r><a:rPr sz="850" b="0" dirty="0"><a:solidFill><a:srgbClr val="A8FF78"/></a:solidFill><a:latin typeface="Consolas"/></a:rPr><a:t>    _rb.gravityScale = CalcGravityScale(v0, maxJumpApexTime);</a:t></a:r></a:p><a:p><a:pPr algn="l" indent="0" marL="0" spc="-100"/><a:r><a:rPr sz="850" b="0" dirty="0"><a:solidFill><a:srgbClr val="A8FF78"/></a:solidFill><a:latin typeface="Consolas"/></a:rPr><a:t>    _rb.linearVelocity = new Vector2(velX, v0);</a:t></a:r></a:p><a:p><a:pPr algn="l" indent="0" marL="0" spc="-100"/><a:r><a:rPr sz="850" b="0" dirty="0"><a:solidFill><a:srgbClr val="A8FF78"/></a:solidFill><a:latin typeface="Consolas"/></a:rPr><a:t>    _hasDoubleJump = true;</a:t></a:r></a:p><a:p><a:pPr algn="l" indent="0" marL="0" spc="-100"/><a:r><a:rPr sz="850" b="0" dirty="0"><a:solidFill><a:srgbClr val="FD971F"/></a:solidFill><a:latin typeface="Consolas"/></a:rPr><a:t>}</a:t></a:r></a:p><a:p><a:pPr spc="-100"/><a:endParaRPr/></a:p><a:p><a:pPr algn="l" indent="0" marL="0" spc="-100"/><a:r><a:rPr sz="850" b="0" dirty="0"><a:solidFill><a:srgbClr val="FD971F"/></a:solidFill><a:latin typeface="Consolas"/></a:rPr><a:t>float CalcGravityScale(float v, float t) {</a:t></a:r></a:p><a:p><a:pPr algn="l" indent="0" marL="0" spc="-100"/><a:r><a:rPr sz="850" b="0" dirty="0"><a:solidFill><a:srgbClr val="888888"/></a:solidFill><a:latin typeface="Consolas"/></a:rPr><a:t>    // g = v / (|gravity| * apexTime)</a:t></a:r></a:p><a:p><a:pPr algn="l" indent="0" marL="0" spc="-100"/><a:r><a:rPr sz="850" b="0" dirty="0"><a:solidFill><a:srgbClr val="A8FF78"/></a:solidFill><a:latin typeface="Consolas"/></a:rPr><a:t>    return v / (Mathf.Abs(Physics2D.gravity.y) * t);</a:t></a:r></a:p><a:p><a:pPr algn="l" indent="0" marL="0" spc="-100"/><a:r><a:rPr sz="850" b="0" dirty="0"><a:solidFill><a:srgbClr val="FD971F"/></a:solidFill><a:latin typeface="Consolas"/></a:rPr><a:t>}</a:t></a:r></a:p></p:txBody></p:sp><p:sp><p:nvSpPr><p:cNvPr id="14" name="RT2"/><p:cNvSpPr txBox="1"/><p:nvPr/></p:nvSpPr><p:spPr><a:xfrm><a:off x="6100000" y="3810000"/><a:ext cx="5900000" cy="380000"/></a:xfrm><a:prstGeom prst="rect"><a:avLst/></a:prstGeom><a:noFill/><a:ln><a:noFill/></a:ln></p:spPr><p:txBody><a:bodyPr wrap="square" lIns="91440" rIns="91440" tIns="45720" bIns="45720"><a:spAutoFit/></a:bodyPr><a:lstStyle/><a:p><a:pPr algn="l" indent="0" marL="0" spc="-100"/><a:r><a:rPr sz="1500" b="1" dirty="0"><a:solidFill><a:srgbClr val="E94F37"/></a:solidFill></a:rPr><a:t>배고픔 디버프 — 이벤트 기반 스탯 조정</a:t></a:r></a:p></p:txBody></p:sp><p:sp><p:nvSpPr><p:cNvPr id="15" name="rect15"/><p:cNvSpPr/><p:nvPr/></p:nvSpPr><p:spPr><a:xfrm><a:off x="6100000" y="4190000"/><a:ext cx="5900000" cy="2350000"/></a:xfrm><a:prstGeom prst="rect"><a:avLst/></a:prstGeom><a:solidFill><a:srgbClr val="0A0A1A"/></a:solidFill><a:ln><a:noFill/></a:ln></p:spPr><p:txBody><a:bodyPr/><a:lstStyle/><a:p><a:endParaRPr/></a:p></p:txBody></p:sp><p:sp><p:nvSpPr><p:cNvPr id="16" name="RC2"/><p:cNvSpPr txBox="1"/><p:nvPr/></p:nvSpPr><p:spPr><a:xfrm><a:off x="6191440" y="4236720"/><a:ext cx="5717280" cy="2303280"/></a:xfrm><a:prstGeom prst="rect"><a:avLst/></a:prstGeom><a:noFill/><a:ln><a:noFill/></a:ln></p:spPr><p:txBody><a:bodyPr wrap="square" lIns="91440" rIns="91440" tIns="45720" bIns="45720"><a:spAutoFit/></a:bodyPr><a:lstStyle/><a:p><a:pPr algn="l" indent="0" marL="0" spc="-100"/><a:r><a:rPr sz="850" b="0" dirty="0"><a:solidFill><a:srgbClr val="FD971F"/></a:solidFill><a:latin typeface="Consolas"/></a:rPr><a:t>void OnHungerChanged(float current, float max) {</a:t></a:r></a:p><a:p><a:pPr algn="l" indent="0" marL="0" spc="-100"/><a:r><a:rPr sz="850" b="0" dirty="0"><a:solidFill><a:srgbClr val="A8FF78"/></a:solidFill><a:latin typeface="Consolas"/></a:rPr><a:t>    bool hungry = current <= 0f;</a:t></a:r></a:p><a:p><a:pPr algn="l" indent="0" marL="0" spc="-100"/><a:r><a:rPr sz="850" b="0" dirty="0"><a:solidFill><a:srgbClr val="A8FF78"/></a:solidFill><a:latin typeface="Consolas"/></a:rPr><a:t>    if (_isHungry == hungry) return;</a:t></a:r></a:p><a:p><a:pPr algn="l" indent="0" marL="0" spc="-100"/><a:r><a:rPr sz="850" b="0" dirty="0"><a:solidFill><a:srgbClr val="A8FF78"/></a:solidFill><a:latin typeface="Consolas"/></a:rPr><a:t>    _isHungry = hungry;</a:t></a:r></a:p><a:p><a:pPr spc="-100"/><a:endParaRPr/></a:p><a:p><a:pPr algn="l" indent="0" marL="0" spc="-100"/><a:r><a:rPr sz="850" b="0" dirty="0"><a:solidFill><a:srgbClr val="A8FF78"/></a:solidFill><a:latin typeface="Consolas"/></a:rPr><a:t>    float mult = hungry ? hungerDebuffMultiplier : 1f;</a:t></a:r></a:p><a:p><a:pPr algn="l" indent="0" marL="0" spc="-100"/><a:r><a:rPr sz="850" b="0" dirty="0"><a:solidFill><a:srgbClr val="A8FF78"/></a:solidFill><a:latin typeface="Consolas"/></a:rPr><a:t>    moveSpeed     = _baseMoveSpeed     * mult;</a:t></a:r></a:p><a:p><a:pPr algn="l" indent="0" marL="0" spc="-100"/><a:r><a:rPr sz="850" b="0" dirty="0"><a:solidFill><a:srgbClr val="A8FF78"/></a:solidFill><a:latin typeface="Consolas"/></a:rPr><a:t>    dashForce     = _baseDashForce     * mult;</a:t></a:r></a:p><a:p><a:pPr algn="l" indent="0" marL="0" spc="-100"/><a:r><a:rPr sz="850" b="0" dirty="0"><a:solidFill><a:srgbClr val="A8FF78"/></a:solidFill><a:latin typeface="Consolas"/></a:rPr><a:t>    maxJumpHeight = _baseMaxJumpHeight * mult;</a:t></a:r></a:p><a:p><a:pPr algn="l" indent="0" marL="0" spc="-100"/><a:r><a:rPr sz="850" b="0" dirty="0"><a:solidFill><a:srgbClr val="FD971F"/></a:solidFill><a:latin typeface="Consolas"/></a:rPr><a:t>}</a:t></a:r></a:p></p:txBody></p:sp></p:spTree></p:cSld><p:clrMapOvr><a:masterClrMapping/></p:clrMapOvr></p:sld>
